imppat_downloader/__init__.py
imppat_downloader/cli.py
imppat_downloader-1.0.2.dist-info/licenses/LICENSE.txt
imppat_downloader-1.0.2.dist-info/METADATA
imppat_downloader-1.0.2.dist-info/WHEEL
imppat_downloader-1.0.2.dist-info/entry_points.txt
imppat_downloader-1.0.2.dist-info/top_level.txt
imppat_downloader-1.0.2.dist-info/RECORD
